thonny_flash_microbitio-0.1.dist-info/DESCRIPTION.rst
thonny_flash_microbitio-0.1.dist-info/METADATA
thonny_flash_microbitio-0.1.dist-info/RECORD
thonny_flash_microbitio-0.1.dist-info/WHEEL
thonny_flash_microbitio-0.1.dist-info/metadata.json
thonny_flash_microbitio-0.1.dist-info/top_level.txt
thonnycontrib/flash-microbitio/__init__.py
thonnycontrib/flash-microbitio/res/bitio.hex
thonnycontrib/flash-microbitio/res/bitio.png
thonnycontrib/flash-microbitio/res/run-flashio.piskel
thonnycontrib/flash-microbitio/res/run.flash_io.gif
